kecam/__init__.py
keras_cv_attention_models/__init__.py
keras_cv_attention_models/backend.py
keras_cv_attention_models/common_layers.py
keras_cv_attention_models/download_and_load.py
keras_cv_attention_models/keras_core_functional.py
keras_cv_attention_models/models.py
keras_cv_attention_models/plot_func.py
keras_cv_attention_models/test_images.py
keras_cv_attention_models/tf_functional.py
keras_cv_attention_models/version.py
keras_cv_attention_models/aotnet/__init__.py
keras_cv_attention_models/aotnet/aotnet.py
keras_cv_attention_models/attention_layers/__init__.py
keras_cv_attention_models/beit/__init__.py
keras_cv_attention_models/beit/beit.py
keras_cv_attention_models/beit/dinov2.py
keras_cv_attention_models/beit/eva.py
keras_cv_attention_models/beit/eva02.py
keras_cv_attention_models/beit/flexivit.py
keras_cv_attention_models/beit/meta_transformer.py
keras_cv_attention_models/beit/vit.py
keras_cv_attention_models/botnet/__init__.py
keras_cv_attention_models/botnet/botnet.py
keras_cv_attention_models/caformer/__init__.py
keras_cv_attention_models/caformer/caformer.py
keras_cv_attention_models/clip/__init__.py
keras_cv_attention_models/clip/models.py
keras_cv_attention_models/clip/tf_data.py
keras_cv_attention_models/clip/tokenizer.py
keras_cv_attention_models/clip/torch_data.py
keras_cv_attention_models/cmt/__init__.py
keras_cv_attention_models/cmt/cmt.py
keras_cv_attention_models/coat/__init__.py
keras_cv_attention_models/coat/coat.py
keras_cv_attention_models/coatnet/__init__.py
keras_cv_attention_models/coatnet/coatnet.py
keras_cv_attention_models/coco/__init__.py
keras_cv_attention_models/coco/anchors_func.py
keras_cv_attention_models/coco/eval_func.py
keras_cv_attention_models/coco/info.py
keras_cv_attention_models/coco/tf_data.py
keras_cv_attention_models/coco/tf_losses.py
keras_cv_attention_models/coco/torch_data.py
keras_cv_attention_models/coco/torch_losses.py
keras_cv_attention_models/convnext/__init__.py
keras_cv_attention_models/convnext/convnext.py
kecam-1.4.2.dist-info/LICENSE
kecam-1.4.2.dist-info/METADATA
kecam-1.4.2.dist-info/WHEEL
kecam-1.4.2.dist-info/top_level.txt
kecam-1.4.2.dist-info/RECORD
