Metadata-Version: 2.1
Name: kecam
Version: 1.4.2
Summary: Tensorflow keras computer vision attention models. Alias kecam. https://github.com/leondgarse/keras_cv_attention_models
Home-page: https://github.com/leondgarse/keras_cv_attention_models
Author: Leondgarse
Author-email: leondgarse@gmail.com
License: Apache 2.0
Keywords: tensorflow keras cv attention pretrained models kecam
Platform: UNKNOWN
Classifier: Development Status :: 3 - Alpha
Classifier: Intended Audience :: Developers
Classifier: Intended Audience :: Science/Research
Classifier: License :: OSI Approved :: Apache Software License
Classifier: Programming Language :: Python :: 3.6
Classifier: Programming Language :: Python :: 3.7
Classifier: Programming Language :: Python :: 3.8
Classifier: Topic :: Scientific/Engineering
Classifier: Topic :: Scientific/Engineering :: Artificial Intelligence
Classifier: Topic :: Software Development
Classifier: Topic :: Software Development :: Libraries
Classifier: Topic :: Software Development :: Libraries :: Python Modules
Requires-Python: >=3.6
License-File: LICENSE
Requires-Dist: h5py
Requires-Dist: pillow
Requires-Dist: tqdm
Requires-Dist: ftfy
Requires-Dist: regex
